Workbook

Sheet Segment Data
A1: PepsiCo Segment Revenue and Operating Profit ($ millions)
A2: Source: PepsiCo Annual Reports (10-K), SEC EDGAR, FY2019–FY2025
A3: Note: Blue values are hardcoded from filings. 2019–2022 use the original 7-segment structure. 2023–2025 use the recast 6-segment structure effective Q1 2025.
A5: 2019–2022: Original Seven-Segment Structure
A6: Segment | B6: 2019 Revenue | C6: 2019 Op Profit | D6: 2020 Revenue | E6: 2020 Op Profit | F6: 2021 Revenue | G6: 2021 Op Profit | H6: 2022 Revenue | I6: 2022 Op Profit
A7: FLNA | B7: 17078 | C7: 5258 | D7: 18189 | E7: 5340 | F7: 19608 | G7: 5633 | H7: 23291 | I7: 6135
A8: QFNA | B8: 2482 | C8: 544 | D8: 2742 | E8: 669 | F8: 2751 | G8: 578 | H8: 3160 | I8: 604
A9: PBNA | B9: 21730 | C9: 2179 | D9: 22559 | E9: 1937 | F9: 25276 | G9: 2442 | H9: 26213 | I9: 5426
A10: LatAm | B10: 7573 | C10: 1141 | D10: 6942 | E10: 1033 | F10: 8108 | G10: 1369 | H10: 9776 | I10: 1627
A11: Europe | B11: 11728 | C11: 1327 | D11: 11922 | E11: 1353 | F11: 13038 | G11: 1292 | H11: 12724 | I11: -1380
A12: AMESA | B12: 3651 | C12: 671 | D12: 4573 | E12: 600 | F12: 6078 | G12: 858 | H12: 6438 | I12: 666
A13: APAC | B13: 2919 | C13: 477 | D13: 3445 | E13: 590 | F13: 4615 | G13: 673 | H13: 4787 | I13: 537
A14: Total | B14: =SUM(B7:B13) | C14: =SUM(C7:C13) | D14: =SUM(D7:D13) | E14: =SUM(E7:E13) | F14: =SUM(F7:F13) | G14: =SUM(G7:G13) | H14: =SUM(H7:H13) | I14: =SUM(I7:I13)
A16: 2023–2025: Recast Six-Segment Structure (effective Q1 2025)
A17: Segment | B17: 2023 Revenue | C17: 2023 Op Profit | D17: 2024 Revenue | E17: 2024 Op Profit | F17: 2025 Revenue | G17: 2025 Op Profit
A18: PFNA | B18: 28015 | C18: 7247 | D18: 27431 | E18: 6619 | F18: 27528 | G18: 6173
A19: PBNA | B19: 27626 | C19: 2584 | D19: 27769 | E19: 2302 | F19: 28197 | G19: 1089
A20: IB Franchise | B20: 4559 | C20: 567 | D20: 4879 | E20: 1462 | F20: 4997 | G20: 1769
A21: EMEA | B21: 16210 | C21: 1764 | D21: 16658 | E21: 1971 | F21: 18025 | G21: 2106
A22: LatAm Foods | B22: 10576 | C22: 1898 | D22: 10568 | E22: 2052 | F22: 10549 | G22: 2010
A23: Asia Pacific Foods | B23: 4485 | C23: 301 | D23: 4549 | E23: 377 | F23: 4629 | G23: 369
A24: Total | B24: =SUM(B18:B23) | C24: =SUM(C18:C23) | D24: =SUM(D18:D23) | E24: =SUM(E18:E23) | F24: =SUM(F18:F23) | G24: =SUM(G18:G23)

Sheet Segment Margins
A1: PepsiCo Segment Operating Margins (%)
A2: Operating Margin = Operating Profit / Revenue. Calculated from Segment Data sheet.
A4: 2019–2022: Original Seven-Segment Structure
A5: Segment | B5: 2019 Margin | C5: 2020 Margin | D5: 2021 Margin | E5: 2022 Margin
A6: FLNA | B6: ='Segment Data'!C7/'Segment Data'!B7 | C6: ='Segment Data'!E7/'Segment Data'!D7 | D6: ='Segment Data'!G7/'Segment Data'!F7 | E6: ='Segment Data'!I7/'Segment Data'!H7
A7: QFNA | B7: ='Segment Data'!C8/'Segment Data'!B8 | C7: ='Segment Data'!E8/'Segment Data'!D8 | D7: ='Segment Data'!G8/'Segment Data'!F8 | E7: ='Segment Data'!I8/'Segment Data'!H8
A8: PBNA | B8: ='Segment Data'!C9/'Segment Data'!B9 | C8: ='Segment Data'!E9/'Segment Data'!D9 | D8: ='Segment Data'!G9/'Segment Data'!F9 | E8: ='Segment Data'!I9/'Segment Data'!H9
A9: LatAm | B9: ='Segment Data'!C10/'Segment Data'!B10 | C9: ='Segment Data'!E10/'Segment Data'!D10 | D9: ='Segment Data'!G10/'Segment Data'!F10 | E9: ='Segment Data'!I10/'Segment Data'!H10
A10: Europe | B10: ='Segment Data'!C11/'Segment Data'!B11 | C10: ='Segment Data'!E11/'Segment Data'!D11 | D10: ='Segment Data'!G11/'Segment Data'!F11 | E10: ='Segment Data'!I11/'Segment Data'!H11
A11: AMESA | B11: ='Segment Data'!C12/'Segment Data'!B12 | C11: ='Segment Data'!E12/'Segment Data'!D12 | D11: ='Segment Data'!G12/'Segment Data'!F12 | E11: ='Segment Data'!I12/'Segment Data'!H12
A12: APAC | B12: ='Segment Data'!C13/'Segment Data'!B13 | C12: ='Segment Data'!E13/'Segment Data'!D13 | D12: ='Segment Data'!G13/'Segment Data'!F13 | E12: ='Segment Data'!I13/'Segment Data'!H13
A14: 2023–2025: Recast Six-Segment Structure
A15: Segment | B15: 2023 Margin | C15: 2024 Margin | D15: 2025 Margin
A16: PFNA | B16: ='Segment Data'!C18/'Segment Data'!B18 | C16: ='Segment Data'!E18/'Segment Data'!D18 | D16: ='Segment Data'!G18/'Segment Data'!F18
A17: PBNA | B17: ='Segment Data'!C19/'Segment Data'!B19 | C17: ='Segment Data'!E19/'Segment Data'!D19 | D17: ='Segment Data'!G19/'Segment Data'!F19
A18: IB Franchise | B18: ='Segment Data'!C20/'Segment Data'!B20 | C18: ='Segment Data'!E20/'Segment Data'!D20 | D18: ='Segment Data'!G20/'Segment Data'!F20
A19: EMEA | B19: ='Segment Data'!C21/'Segment Data'!B21 | C19: ='Segment Data'!E21/'Segment Data'!D21 | D19: ='Segment Data'!G21/'Segment Data'!F21
A20: LatAm Foods | B20: ='Segment Data'!C22/'Segment Data'!B22 | C20: ='Segment Data'!E22/'Segment Data'!D22 | D20: ='Segment Data'!G22/'Segment Data'!F22
A21: Asia Pacific Foods | B21: ='Segment Data'!C23/'Segment Data'!B23 | C21: ='Segment Data'!E23/'Segment Data'!D23 | D21: ='Segment Data'!G23/'Segment Data'!F23

Sheet Raw Data
B1: 2019 | C1: 2020 | D1: 2021 | E1: 2022 | F1: 2023 | G1: 2024 | H1: 2025
A2: Net Revenue | B2: 67161 | C2: 70372 | D2: 79474 | E2: 86392 | F2: 91471 | G2: 91854 | H2: 93925
A3: Cost of Sales | B3: 30132 | C3: 31797 | D3: 37075 | E3: 40576 | F3: 41881 | G3: 41744 | H3: 43066
A4: Gross Profit | B4: 37029 | C4: 38575 | D4: 42399 | E4: 45816 | F4: 49590 | G4: 50110 | H4: 50859
A5: Net Income | B5: 7314 | C5: 7120 | D5: 7618 | E5: 8910 | F5: 9074 | G5: 9578 | H5: 8240
A6: Total Assets | B6: 78547 | C6: 92918 | D6: 92377 | E6: 92187 | F6: 100495 | G6: 99467 | H6: 107399
A7: Shareholders Equity | B7: 14786 | C7: 13454 | D7: 16043 | E7: 17149 | F7: 18503 | G7: 18041 | H7: 20406
